ariths_gen/__init__.py
ariths_gen/core/__init__.py
ariths_gen/core/cgp_circuit.py
ariths_gen/core/arithmetic_circuits/__init__.py
ariths_gen/core/arithmetic_circuits/general_circuit.py
ariths_gen/core/arithmetic_circuits/multiplier_circuit.py
ariths_gen/core/logic_gate_circuits/__init__.py
ariths_gen/core/logic_gate_circuits/logic_gate_circuit.py
ariths_gen/core/one_bit_circuits/__init__.py
ariths_gen/core/one_bit_circuits/four_input_one_bit_circuit.py
ariths_gen/core/one_bit_circuits/three_input_one_bit_circuit.py
ariths_gen/core/one_bit_circuits/two_input_one_bit_circuit.py
ariths_gen/multi_bit_circuits/__init__.py
ariths_gen/multi_bit_circuits/adders/__init__.py
ariths_gen/multi_bit_circuits/adders/brent_kung_adder.py
ariths_gen/multi_bit_circuits/adders/carry_increment_adder.py
ariths_gen/multi_bit_circuits/adders/carry_lookahead_adder.py
ariths_gen/multi_bit_circuits/adders/carry_save_adder.py
ariths_gen/multi_bit_circuits/adders/carry_select_adder.py
ariths_gen/multi_bit_circuits/adders/carry_skip_adder.py
ariths_gen/multi_bit_circuits/adders/conditional_sum_adder.py
ariths_gen/multi_bit_circuits/adders/han_carlson_adder.py
ariths_gen/multi_bit_circuits/adders/knowles_adder.py
ariths_gen/multi_bit_circuits/adders/kogge_stone_adder.py
ariths_gen/multi_bit_circuits/adders/ladner_fischer_adder.py
ariths_gen/multi_bit_circuits/adders/pg_ripple_carry_adder.py
ariths_gen/multi_bit_circuits/adders/ripple_carry_adder.py
ariths_gen/multi_bit_circuits/adders/sklansky_adder.py
ariths_gen/multi_bit_circuits/approximate_adders/__init__.py
ariths_gen/multi_bit_circuits/approximate_adders/quad.py
ariths_gen/multi_bit_circuits/approximate_multipliers/__init__.py
ariths_gen/multi_bit_circuits/approximate_multipliers/broken_array_multiplier.py
ariths_gen/multi_bit_circuits/approximate_multipliers/broken_carry_save_multiplier.py
ariths_gen/multi_bit_circuits/approximate_multipliers/recursive_multiplier.py
ariths_gen-1.1.4.dist-info/METADATA
ariths_gen-1.1.4.dist-info/WHEEL
ariths_gen-1.1.4.dist-info/top_level.txt
ariths_gen-1.1.4.dist-info/RECORD
