Metadata-Version: 2.4
Name: ariths_gen
Version: 1.1.4
Summary: Arithmetic circuits generator to Verilog, BLIF, C etc.
Home-page: https://github.com/ehw-fit/ariths-gen
Author: Jan Klhufek, Vojtech Mrazek
Author-email: iklhufek@fit.vutbr.cz
License: MIT
Project-URL: Code, https://github.com/ehw-fit/ariths-gen
Project-URL: Issue tracker, https://github.com/ehw-fit/ariths-gen/issues
Requires-Python: >=3.8
